README
setup.py
treeshape/__init__.py
treeshape/_dwim.py
treeshape/_fixtures.py
treeshape/_matchers.py
treeshape/_treeshape.py
treeshape.egg-info/PKG-INFO
treeshape.egg-info/SOURCES.txt
treeshape.egg-info/dependency_links.txt
treeshape.egg-info/not-zip-safe
treeshape.egg-info/requires.txt
treeshape.egg-info/top_level.txt
treeshape/tests/__init__.py
treeshape/tests/test_dwim.py
treeshape/tests/test_fixture.py
treeshape/tests/test_matchers.py
treeshape/tests/test_treeshape.py