Metadata-Version: 1.1
Name: treeshape
Version: 0.2.0
Summary: Quickly make files and directory structures.
Home-page: UNKNOWN
Author: Jonathan Lange
Author-email: jml@mumak.net
License: UNKNOWN
Platform: UNKNOWN
Classifier: Development Status :: 6 - Mature
Classifier: Intended Audience :: Developers
Classifier: License :: OSI Approved :: BSD License
Classifier: License :: OSI Approved :: Apache Software License
Classifier: Operating System :: OS Independent
Classifier: Programming Language :: Python
Classifier: Topic :: Software Development :: Quality Assurance
Classifier: Topic :: Software Development :: Testing
